{
    "english":  {
                    "letter_type":  "RENEWAL INTIMATION 06352",
                    "letter_date":  "06-06-2026",
                    "customer_name":  "INFONOVA SERVICES PVT LTD 06352",
                    "customer_address":  "Plot 92, Industrial Area, Sector 3, 6452 Road, LUCKNOW, UTTAR PRADESH",
                    "customer_city":  "LUCKNOW",
                    "customer_state":  "UTTAR PRADESH",
                    "customer_pincode":  "226259",
                    "customer_contact_no":  "9750301488",
                    "customer_gst_number":  "09AABC2576D1Z8",
                    "customer_id":  "20240006352",
                    "servicing_branch":  "LUCKNOW",
                    "insurer_name":  "Heritage General Insurance Company 06352",
                    "branch_office_address":  "Suite 852, 13TH FLOOR, BUSINESS PARK, LUCKNOW - 226259, UTTAR PRADESH",
                    "branch_phone":  "1800 102 6352",
                    "insurer_gst_number":  "09AAHCN7984K1Z2",
                    "imd_code":  "BRC0006852",
                    "imd_name":  "WINTAGE INSURANCE BROKERS LIMITED 06352",
                    "imd_aadhar_no":  "100000006352",
                    "reference_subject":  "Renewal of your Group Personal Accident Policy Ref 06352",
                    "policy_number":  "P0142206352/8352/156352",
                    "product_name":  "Group Personal Accident",
                    "risk_description":  "Corporate employee benefit risk 06352",
                    "policy_expiry_date":  "02-11-2026",
                    "renewal_date":  "02-11-2026",
                    "corporate_registered_office":  "Heritage Tower, Floor 23, Corporate District, LUCKNOW - 226259, UTTAR PRADESH, India",
                    "care_line":  "1800 102 8372",
                    "email":  "support06352@heritageinsurance.co.in",
                    "website":  "www.heritageinsurance06352.co.in",
                    "irda_registration_no":  "152",
                    "cin":  "U6600009MH2011PLC240352",
                    "uin":  "HERIGP06352V032022",
                    "signatory":  "Authorised Signatory 06352",
                    "transactionTable":  {
                                             "heading":  {
                                                             "Policy_Number":  "Policy Number 06352",
                                                             "Product_Name":  "Product Name 06352",
                                                             "Risk_Description":  "Risk Description 06352",
                                                             "Renewal_Date":  "Renewal Date 06352"
                                                         },
                                             "data":  [
                                                          {
                                                              "Policy_Number":  "P0142206352/8352/156352",
                                                              "Product_Name":  "Group Personal Accident",
                                                              "Risk_Description":  "Corporate employee benefit risk 06352",
                                                              "Renewal_Date":  "02-11-2026"
                                                          }
                                                      ]
                                         }
                }
}
