{
    "english":  {
                    "letter_type":  "RENEWAL INTIMATION 01555",
                    "letter_date":  "09-06-2026",
                    "customer_name":  "NEXORA SERVICES PVT LTD 01555",
                    "customer_address":  "Plot 695, Industrial Area, Sector 6, 1655 Road, BENGALURU, KARNATAKA",
                    "customer_city":  "BENGALURU",
                    "customer_state":  "KARNATAKA",
                    "customer_pincode":  "560592",
                    "customer_contact_no":  "9712314045",
                    "customer_gst_number":  "29AABC0215D1Z8",
                    "customer_id":  "20240001555",
                    "servicing_branch":  "BENGALURU",
                    "insurer_name":  "Heritage General Insurance Company 01555",
                    "branch_office_address":  "Suite 855, 16TH FLOOR, BUSINESS PARK, BENGALURU - 560592, KARNATAKA",
                    "branch_phone":  "1800 102 1555",
                    "insurer_gst_number":  "29AAHCN6435K1Z2",
                    "imd_code":  "BRC0002055",
                    "imd_name":  "WINTAGE INSURANCE BROKERS LIMITED 01555",
                    "imd_aadhar_no":  "100000001555",
                    "reference_subject":  "Renewal of your Corporate Health Protect Policy Ref 01555",
                    "policy_number":  "P0142201555/8555/151555",
                    "product_name":  "Corporate Health Protect",
                    "risk_description":  "Corporate employee benefit risk 01555",
                    "policy_expiry_date":  "11-09-2026",
                    "renewal_date":  "11-09-2026",
                    "corporate_registered_office":  "Heritage Tower, Floor 26, Corporate District, BENGALURU - 560592, KARNATAKA, India",
                    "care_line":  "1800 102 3575",
                    "email":  "support01555@heritageinsurance.co.in",
                    "website":  "www.heritageinsurance01555.co.in",
                    "irda_registration_no":  "755",
                    "cin":  "U6600029MH2011PLC235555",
                    "uin":  "HERIGP01555V032022",
                    "signatory":  "Authorised Signatory 01555",
                    "transactionTable":  {
                                             "heading":  {
                                                             "Policy_Number":  "Policy Number 01555",
                                                             "Product_Name":  "Product Name 01555",
                                                             "Risk_Description":  "Risk Description 01555",
                                                             "Renewal_Date":  "Renewal Date 01555"
                                                         },
                                             "data":  [
                                                          {
                                                              "Policy_Number":  "P0142201555/8555/151555",
                                                              "Product_Name":  "Corporate Health Protect",
                                                              "Risk_Description":  "Corporate employee benefit risk 01555",
                                                              "Renewal_Date":  "11-09-2026"
                                                          }
                                                      ]
                                         }
                }
}
