{
    "english":  {
                    "letter_type":  "RENEWAL INTIMATION 07956",
                    "letter_date":  "21-05-2026",
                    "customer_name":  "FINEDGE SERVICES PVT LTD 07956",
                    "customer_address":  "Plot 796, Industrial Area, Sector 7, 8056 Road, CHENNAI, TAMIL NADU",
                    "customer_city":  "CHENNAI",
                    "customer_state":  "TAMIL NADU",
                    "customer_pincode":  "600666",
                    "customer_contact_no":  "9763003564",
                    "customer_gst_number":  "33AABC3428D1Z1",
                    "customer_id":  "20240007956",
                    "servicing_branch":  "CHENNAI",
                    "insurer_name":  "Heritage General Insurance Company 07956",
                    "branch_office_address":  "Suite 856, 17TH FLOOR, BUSINESS PARK, CHENNAI - 600666, TAMIL NADU",
                    "branch_phone":  "1800 102 7956",
                    "insurer_gst_number":  "33AAHCN5252K1Z4",
                    "imd_code":  "BRC0008456",
                    "imd_name":  "WINTAGE INSURANCE BROKERS LIMITED 07956",
                    "imd_aadhar_no":  "100000007956",
                    "reference_subject":  "Renewal of your GroupHealthInsurance Policy Ref 07956",
                    "policy_number":  "P0142207956/8956/157956",
                    "product_name":  "GroupHealthInsurance",
                    "risk_description":  "Corporate employee benefit risk 07956",
                    "policy_expiry_date":  "26-03-2027",
                    "renewal_date":  "26-03-2027",
                    "corporate_registered_office":  "Heritage Tower, Floor 7, Corporate District, CHENNAI - 600666, TAMIL NADU, India",
                    "care_line":  "1800 102 9976",
                    "email":  "support07956@heritageinsurance.co.in",
                    "website":  "www.heritageinsurance07956.co.in",
                    "irda_registration_no":  "856",
                    "cin":  "U6600033MH2011PLC241956",
                    "uin":  "HERIGP07956V032022",
                    "signatory":  "Authorised Signatory 07956",
                    "transactionTable":  {
                                             "heading":  {
                                                             "Policy_Number":  "Policy Number 07956",
                                                             "Product_Name":  "Product Name 07956",
                                                             "Risk_Description":  "Risk Description 07956",
                                                             "Renewal_Date":  "Renewal Date 07956"
                                                         },
                                             "data":  [
                                                          {
                                                              "Policy_Number":  "P0142207956/8956/157956",
                                                              "Product_Name":  "GroupHealthInsurance",
                                                              "Risk_Description":  "Corporate employee benefit risk 07956",
                                                              "Renewal_Date":  "26-03-2027"
                                                          }
                                                      ]
                                         }
                }
}
