{
    "english":  {
                    "letter_type":  "RENEWAL INTIMATION 04599",
                    "letter_date":  "24-05-2026",
                    "customer_name":  "SOFTBRIDGE SERVICES PVT LTD 04599",
                    "customer_address":  "Plot 139, Industrial Area, Sector 50, 4699 Road, JAIPUR, RAJASTHAN",
                    "customer_city":  "JAIPUR",
                    "customer_state":  "RAJASTHAN",
                    "customer_pincode":  "302333",
                    "customer_contact_no":  "9736419481",
                    "customer_gst_number":  "08AABC9787D1Z1",
                    "customer_id":  "20240004599",
                    "servicing_branch":  "JAIPUR",
                    "insurer_name":  "Heritage General Insurance Company 04599",
                    "branch_office_address":  "Suite 699, 20TH FLOOR, BUSINESS PARK, JAIPUR - 302333, RAJASTHAN",
                    "branch_phone":  "1800 102 4599",
                    "insurer_gst_number":  "08AAHCN8183K1Z4",
                    "imd_code":  "BRC0005099",
                    "imd_name":  "WINTAGE INSURANCE BROKERS LIMITED 04599",
                    "imd_aadhar_no":  "100000004599",
                    "reference_subject":  "Renewal of your Employee Health Cover Policy Ref 04599",
                    "policy_number":  "P0142204599/8599/154599",
                    "product_name":  "Employee Health Cover",
                    "risk_description":  "Corporate employee benefit risk 04599",
                    "policy_expiry_date":  "13-01-2027",
                    "renewal_date":  "13-01-2027",
                    "corporate_registered_office":  "Heritage Tower, Floor 10, Corporate District, JAIPUR - 302333, RAJASTHAN, India",
                    "care_line":  "1800 102 6619",
                    "email":  "support04599@heritageinsurance.co.in",
                    "website":  "www.heritageinsurance04599.co.in",
                    "irda_registration_no":  "199",
                    "cin":  "U6600008MH2011PLC238599",
                    "uin":  "HERIGP04599V032022",
                    "signatory":  "Authorised Signatory 04599",
                    "transactionTable":  {
                                             "heading":  {
                                                             "Policy_Number":  "Policy Number 04599",
                                                             "Product_Name":  "Product Name 04599",
                                                             "Risk_Description":  "Risk Description 04599",
                                                             "Renewal_Date":  "Renewal Date 04599"
                                                         },
                                             "data":  [
                                                          {
                                                              "Policy_Number":  "P0142204599/8599/154599",
                                                              "Product_Name":  "Employee Health Cover",
                                                              "Risk_Description":  "Corporate employee benefit risk 04599",
                                                              "Renewal_Date":  "13-01-2027"
                                                          }
                                                      ]
                                         }
                }
}
