{
    "english":  {
                    "letter_type":  "RENEWAL INTIMATION 09326",
                    "letter_date":  "11-05-2026",
                    "customer_name":  "FINEDGE INDUSTRIES PVT LTD 09326",
                    "customer_address":  "Plot 366, Industrial Area, Sector 27, 9426 Road, AHMEDABAD, GUJARAT",
                    "customer_city":  "AHMEDABAD",
                    "customer_state":  "GUJARAT",
                    "customer_pincode":  "380407",
                    "customer_contact_no":  "9773852594",
                    "customer_gst_number":  "24AABC1238D1Z3",
                    "customer_id":  "20240009326",
                    "servicing_branch":  "AHMEDABAD",
                    "insurer_name":  "Heritage General Insurance Company 09326",
                    "branch_office_address":  "Suite 626, 7TH FLOOR, BUSINESS PARK, AHMEDABAD - 380407, GUJARAT",
                    "branch_phone":  "1800 102 9326",
                    "insurer_gst_number":  "24AAHCN8542K1Z6",
                    "imd_code":  "BRC0009826",
                    "imd_name":  "WINTAGE INSURANCE BROKERS LIMITED 09326",
                    "imd_aadhar_no":  "100000009326",
                    "reference_subject":  "Renewal of your GroupHealthInsurance Policy Ref 09326",
                    "policy_number":  "P0142209326/8326/159326",
                    "product_name":  "GroupHealthInsurance",
                    "risk_description":  "Corporate employee benefit risk 09326",
                    "policy_expiry_date":  "26-12-2026",
                    "renewal_date":  "26-12-2026",
                    "corporate_registered_office":  "Heritage Tower, Floor 27, Corporate District, AHMEDABAD - 380407, GUJARAT, India",
                    "care_line":  "1800 102 1346",
                    "email":  "support09326@heritageinsurance.co.in",
                    "website":  "www.heritageinsurance09326.co.in",
                    "irda_registration_no":  "426",
                    "cin":  "U6600024MH2011PLC243326",
                    "uin":  "HERIGP09326V032022",
                    "signatory":  "Authorised Signatory 09326",
                    "transactionTable":  {
                                             "heading":  {
                                                             "Policy_Number":  "Policy Number 09326",
                                                             "Product_Name":  "Product Name 09326",
                                                             "Risk_Description":  "Risk Description 09326",
                                                             "Renewal_Date":  "Renewal Date 09326"
                                                         },
                                             "data":  [
                                                          {
                                                              "Policy_Number":  "P0142209326/8326/159326",
                                                              "Product_Name":  "GroupHealthInsurance",
                                                              "Risk_Description":  "Corporate employee benefit risk 09326",
                                                              "Renewal_Date":  "26-12-2026"
                                                          }
                                                      ]
                                         }
                }
}
