{
    "english":  {
                    "letter_type":  "RENEWAL INTIMATION 07769",
                    "letter_date":  "14-05-2026",
                    "customer_name":  "SOFTBRIDGE SOLUTIONS PVT LTD 07769",
                    "customer_address":  "Plot 609, Industrial Area, Sector 20, 7869 Road, PUNE, MAHARASHTRA",
                    "customer_city":  "PUNE",
                    "customer_state":  "MAHARASHTRA",
                    "customer_pincode":  "411740",
                    "customer_contact_no":  "9761522711",
                    "customer_gst_number":  "27AABC0997D1Z3",
                    "customer_id":  "20240007769",
                    "servicing_branch":  "PUNE",
                    "insurer_name":  "Heritage General Insurance Company 07769",
                    "branch_office_address":  "Suite 669, 10TH FLOOR, BUSINESS PARK, PUNE - 411740, MAHARASHTRA",
                    "branch_phone":  "1800 102 7769",
                    "insurer_gst_number":  "27AAHCN2073K1Z6",
                    "imd_code":  "BRC0008269",
                    "imd_name":  "WINTAGE INSURANCE BROKERS LIMITED 07769",
                    "imd_aadhar_no":  "100000007769",
                    "reference_subject":  "Renewal of your Employee Health Cover Policy Ref 07769",
                    "policy_number":  "P0142207769/8769/157769",
                    "product_name":  "Employee Health Cover",
                    "risk_description":  "Corporate employee benefit risk 07769",
                    "policy_expiry_date":  "20-09-2026",
                    "renewal_date":  "20-09-2026",
                    "corporate_registered_office":  "Heritage Tower, Floor 30, Corporate District, PUNE - 411740, MAHARASHTRA, India",
                    "care_line":  "1800 102 9789",
                    "email":  "support07769@heritageinsurance.co.in",
                    "website":  "www.heritageinsurance07769.co.in",
                    "irda_registration_no":  "669",
                    "cin":  "U6600027MH2011PLC241769",
                    "uin":  "HERIGP07769V032022",
                    "signatory":  "Authorised Signatory 07769",
                    "transactionTable":  {
                                             "heading":  {
                                                             "Policy_Number":  "Policy Number 07769",
                                                             "Product_Name":  "Product Name 07769",
                                                             "Risk_Description":  "Risk Description 07769",
                                                             "Renewal_Date":  "Renewal Date 07769"
                                                         },
                                             "data":  [
                                                          {
                                                              "Policy_Number":  "P0142207769/8769/157769",
                                                              "Product_Name":  "Employee Health Cover",
                                                              "Risk_Description":  "Corporate employee benefit risk 07769",
                                                              "Renewal_Date":  "20-09-2026"
                                                          }
                                                      ]
                                         }
                }
}
