{
    "english":  {
                    "letter_type":  "RENEWAL INTIMATION 03121",
                    "letter_date":  "16-04-2026",
                    "customer_name":  "TECHVISION SOLUTIONS PVT LTD 03121",
                    "customer_address":  "Plot 461, Industrial Area, Sector 22, 3221 Road, PUNE, MAHARASHTRA",
                    "customer_city":  "PUNE",
                    "customer_state":  "MAHARASHTRA",
                    "customer_pincode":  "411592",
                    "customer_contact_no":  "9724715199",
                    "customer_gst_number":  "27AABC0573D1Z8",
                    "customer_id":  "20240003121",
                    "servicing_branch":  "PUNE",
                    "insurer_name":  "Heritage General Insurance Company 03121",
                    "branch_office_address":  "Suite 821, 2TH FLOOR, BUSINESS PARK, PUNE - 411592, MAHARASHTRA",
                    "branch_phone":  "1800 102 3121",
                    "insurer_gst_number":  "27AAHCN3057K1Z2",
                    "imd_code":  "BRC0003621",
                    "imd_name":  "WINTAGE INSURANCE BROKERS LIMITED 03121",
                    "imd_aadhar_no":  "100000003121",
                    "reference_subject":  "Renewal of your GroupHealthInsurance Policy Ref 03121",
                    "policy_number":  "P0142203121/8121/153121",
                    "product_name":  "GroupHealthInsurance",
                    "risk_description":  "Corporate employee benefit risk 03121",
                    "policy_expiry_date":  "26-12-2026",
                    "renewal_date":  "26-12-2026",
                    "corporate_registered_office":  "Heritage Tower, Floor 2, Corporate District, PUNE - 411592, MAHARASHTRA, India",
                    "care_line":  "1800 102 5141",
                    "email":  "support03121@heritageinsurance.co.in",
                    "website":  "www.heritageinsurance03121.co.in",
                    "irda_registration_no":  "521",
                    "cin":  "U6600027MH2011PLC237121",
                    "uin":  "HERIGP03121V032022",
                    "signatory":  "Authorised Signatory 03121",
                    "transactionTable":  {
                                             "heading":  {
                                                             "Policy_Number":  "Policy Number 03121",
                                                             "Product_Name":  "Product Name 03121",
                                                             "Risk_Description":  "Risk Description 03121",
                                                             "Renewal_Date":  "Renewal Date 03121"
                                                         },
                                             "data":  [
                                                          {
                                                              "Policy_Number":  "P0142203121/8121/153121",
                                                              "Product_Name":  "GroupHealthInsurance",
                                                              "Risk_Description":  "Corporate employee benefit risk 03121",
                                                              "Renewal_Date":  "26-12-2026"
                                                          }
                                                      ]
                                         }
                }
}
