{
    "english":  {
                    "letter_type":  "RENEWAL INTIMATION 02521",
                    "letter_date":  "16-04-2026",
                    "customer_name":  "TECHVISION INDUSTRIES PVT LTD 02521",
                    "customer_address":  "Plot 761, Industrial Area, Sector 22, 2621 Road, PUNE, MAHARASHTRA",
                    "customer_city":  "PUNE",
                    "customer_state":  "MAHARASHTRA",
                    "customer_pincode":  "411370",
                    "customer_contact_no":  "9719963799",
                    "customer_gst_number":  "27AABC2773D1Z2",
                    "customer_id":  "20240002521",
                    "servicing_branch":  "PUNE",
                    "insurer_name":  "Heritage General Insurance Company 02521",
                    "branch_office_address":  "Suite 221, 2TH FLOOR, BUSINESS PARK, PUNE - 411370, MAHARASHTRA",
                    "branch_phone":  "1800 102 2521",
                    "insurer_gst_number":  "27AAHCN2857K1Z5",
                    "imd_code":  "BRC0003021",
                    "imd_name":  "WINTAGE INSURANCE BROKERS LIMITED 02521",
                    "imd_aadhar_no":  "100000002521",
                    "reference_subject":  "Renewal of your GroupHealthInsurance Policy Ref 02521",
                    "policy_number":  "P0142202521/8521/152521",
                    "product_name":  "GroupHealthInsurance",
                    "risk_description":  "Corporate employee benefit risk 02521",
                    "policy_expiry_date":  "05-05-2027",
                    "renewal_date":  "05-05-2027",
                    "corporate_registered_office":  "Heritage Tower, Floor 2, Corporate District, PUNE - 411370, MAHARASHTRA, India",
                    "care_line":  "1800 102 4541",
                    "email":  "support02521@heritageinsurance.co.in",
                    "website":  "www.heritageinsurance02521.co.in",
                    "irda_registration_no":  "821",
                    "cin":  "U6600027MH2011PLC236521",
                    "uin":  "HERIGP02521V032022",
                    "signatory":  "Authorised Signatory 02521",
                    "transactionTable":  {
                                             "heading":  {
                                                             "Policy_Number":  "Policy Number 02521",
                                                             "Product_Name":  "Product Name 02521",
                                                             "Risk_Description":  "Risk Description 02521",
                                                             "Renewal_Date":  "Renewal Date 02521"
                                                         },
                                             "data":  [
                                                          {
                                                              "Policy_Number":  "P0142202521/8521/152521",
                                                              "Product_Name":  "GroupHealthInsurance",
                                                              "Risk_Description":  "Corporate employee benefit risk 02521",
                                                              "Renewal_Date":  "05-05-2027"
                                                          }
                                                      ]
                                         }
                }
}
