{
    "english":  {
                    "letter_type":  "RENEWAL INTIMATION 09077",
                    "letter_date":  "02-05-2026",
                    "customer_name":  "MEDILINK SERVICES PVT LTD 09077",
                    "customer_address":  "Plot 117, Industrial Area, Sector 28, 9177 Road, HYDERABAD, TELANGANA",
                    "customer_city":  "HYDERABAD",
                    "customer_state":  "TELANGANA",
                    "customer_pincode":  "500185",
                    "customer_contact_no":  "9771880763",
                    "customer_gst_number":  "36AABC8001D1Z6",
                    "customer_id":  "20240009077",
                    "servicing_branch":  "HYDERABAD",
                    "insurer_name":  "Heritage General Insurance Company 09077",
                    "branch_office_address":  "Suite 377, 18TH FLOOR, BUSINESS PARK, HYDERABAD - 500185, TELANGANA",
                    "branch_phone":  "1800 102 9077",
                    "insurer_gst_number":  "36AAHCN4309K1Z9",
                    "imd_code":  "BRC0009577",
                    "imd_name":  "WINTAGE INSURANCE BROKERS LIMITED 09077",
                    "imd_aadhar_no":  "100000009077",
                    "reference_subject":  "Renewal of your Group Personal Accident Policy Ref 09077",
                    "policy_number":  "P0142209077/8077/159077",
                    "product_name":  "Group Personal Accident",
                    "risk_description":  "Corporate employee benefit risk 09077",
                    "policy_expiry_date":  "21-04-2027",
                    "renewal_date":  "21-04-2027",
                    "corporate_registered_office":  "Heritage Tower, Floor 18, Corporate District, HYDERABAD - 500185, TELANGANA, India",
                    "care_line":  "1800 102 1097",
                    "email":  "support09077@heritageinsurance.co.in",
                    "website":  "www.heritageinsurance09077.co.in",
                    "irda_registration_no":  "177",
                    "cin":  "U6600036MH2011PLC243077",
                    "uin":  "HERIGP09077V032022",
                    "signatory":  "Authorised Signatory 09077",
                    "transactionTable":  {
                                             "heading":  {
                                                             "Policy_Number":  "Policy Number 09077",
                                                             "Product_Name":  "Product Name 09077",
                                                             "Risk_Description":  "Risk Description 09077",
                                                             "Renewal_Date":  "Renewal Date 09077"
                                                         },
                                             "data":  [
                                                          {
                                                              "Policy_Number":  "P0142209077/8077/159077",
                                                              "Product_Name":  "Group Personal Accident",
                                                              "Risk_Description":  "Corporate employee benefit risk 09077",
                                                              "Renewal_Date":  "21-04-2027"
                                                          }
                                                      ]
                                         }
                }
}
